[{
         "id": "47587401",
         "tipoPropiedad": "DEPARTAMENTO",
         "precioUSD": 160000,
         "fechaUltimaActualizacion": "25-07-2022",
         "terrenoTotal": "180",
         "terrenoEdificado": "180",
         "cantDormitorios": "4",
         "cantBanos": "2",
         "cantCochera": -1,
         "barrio": "CENTRO",
         "ciudad": "CORDOBA",
         "URL": "https://www.zonaprop.com.ar/propiedades/piso-entero-de-4-dorm.-y-patio-sobre-canada-47587401.html"
},{
         "id": "47668235",
         "tipoPropiedad": "DEPARTAMENTO",
         "precioUSD": 69000,
         "fechaUltimaActualizacion": "25-07-2022",
         "terrenoTotal": "1000",
         "terrenoEdificado": "50",
         "cantDormitorios": "1",
         "cantBanos": "1",
         "cantCochera": -1,
         "barrio": "DEPARTAMENTO EN VENTA SOBRE BV. SAN JUAN",
         "ciudad": "CORDOBA",
         "URL": "https://www.zonaprop.com.ar/propiedades/departamento-en-venta-sobre-bv.-san-juan-47668235.html"
},{
         "id": "47439420",
         "tipoPropiedad": "CASA",
         "precioUSD": 48000,
         "fechaUltimaActualizacion": "25-07-2022",
         "terrenoTotal": "100",
         "terrenoEdificado": "75",
         "cantDormitorios": "2",
         "cantBanos": "2",
         "cantCochera": -1,
         "barrio": "COFICO",
         "ciudad": "CORDOBA",
         "URL": "https://www.zonaprop.com.ar/propiedades/vendo-duplex-a-estrenar-2-dorm.-barrio-cerrado-con-47439420.html"
},{
         "id": "48150527",
         "tipoPropiedad": "CASA",
         "precioUSD": 240000,
         "fechaUltimaActualizacion": "25-07-2022",
         "terrenoTotal": "438",
         "terrenoEdificado": "218",
         "cantDormitorios": "3",
         "cantBanos": "3",
         "cantCochera": "1",
         "barrio": "ALEJANDRO CENTENO",
         "ciudad": "CORDOBA",
         "URL": "https://www.zonaprop.com.ar/propiedades/propiedad-de-categoria-en-b-alejandro-centeno-48150527.html"
},{
         "id": "48188910",
         "tipoPropiedad": "DEPARTAMENTO",
         "precioUSD": 85000,
         "fechaUltimaActualizacion": "25-07-2022",
         "terrenoTotal": "120",
         "terrenoEdificado": "40",
         "cantDormitorios": "1",
         "cantBanos": "1",
         "cantCochera": -1,
         "barrio": "NUEVA CORDOBA",
         "ciudad": "CORDOBA",
         "URL": "https://www.zonaprop.com.ar/propiedades/nva.-cba.-1-dor.-gran-terraza-a-estrenar!-48188910.html"
},{
         "id": "48161553",
         "tipoPropiedad": "TERRENOS",
         "precioUSD": 49000,
         "fechaUltimaActualizacion": "25-07-2022",
         "terrenoTotal": "360",
         "terrenoEdificado": -1,
         "cantDormitorios": -1,
         "cantBanos": -1,
         "cantCochera": -1,
         "barrio": "SOLARES DE MANANTIALES",
         "ciudad": "CORDOBA",
         "URL": "https://www.zonaprop.com.ar/propiedades/solares-de-manantiales-2-lotes-colindantes-48161553.html"
},{
         "id": "47944457",
         "tipoPropiedad": "CASA",
         "precioUSD": 90000,
         "fechaUltimaActualizacion": "25-07-2022",
         "terrenoTotal": "250",
         "terrenoEdificado": "140",
         "cantDormitorios": "3",
         "cantBanos": "2",
         "cantCochera": -1,
         "barrio": "JUAN XXIII",
         "ciudad": "CORDOBA",
         "URL": "https://www.zonaprop.com.ar/propiedades/impecable-casa-en-venta-en-b-juan-xxiii-3-dorm.-47944457.html"
},{
         "id": "48243796",
         "tipoPropiedad": "CASA",
         "precioUSD": 239000,
         "fechaUltimaActualizacion": "25-07-2022",
         "terrenoTotal": "355",
         "terrenoEdificado": "302",
         "cantDormitorios": "4",
         "cantBanos": "3",
         "cantCochera": -1,
         "barrio": "URCA",
         "ciudad": "CORDOBA",
         "URL": "https://www.zonaprop.com.ar/propiedades/casa-de-4-dorm.-en-venta-en-urca-48243796.html"
},{
         "id": "48096252",
         "tipoPropiedad": "DEPARTAMENTO",
         "precioUSD": 60000,
         "fechaUltimaActualizacion": "25-07-2022",
         "terrenoTotal": "50",
         "terrenoEdificado": "47",
         "cantDormitorios": "1",
         "cantBanos": "1",
         "cantCochera": -1,
         "barrio": "COFICO",
         "ciudad": "CORDOBA",
         "URL": "https://www.zonaprop.com.ar/propiedades/departamento-venta-1-dormitorio.-cofico-campillo-100.-48096252.html"
},{
         "id": "48267251",
         "tipoPropiedad": "CASA",
         "precioUSD": 140000,
         "fechaUltimaActualizacion": "25-07-2022",
         "terrenoTotal": "1501",
         "terrenoEdificado": "228",
         "cantDormitorios": "3",
         "cantBanos": "1",
         "cantCochera": "3",
         "barrio": "VILLA RETIRO",
         "ciudad": "CORDOBA",
         "URL": "https://www.zonaprop.com.ar/propiedades/casa-en-villa-retiro-cordoba-48267251.html"
},{
         "id": "48327344",
         "tipoPropiedad": "CASA",
         "precioUSD": 98000,
         "fechaUltimaActualizacion": "25-07-2022",
         "terrenoTotal": "180",
         "terrenoEdificado": "120",
         "cantDormitorios": "3",
         "cantBanos": "3",
         "cantCochera": -1,
         "barrio": "PRADOS DE MANANTIALES",
         "ciudad": "CORDOBA",
         "URL": "https://www.zonaprop.com.ar/propiedades/duplex-en-venta-prados-de-manantiales-3-dorm.-48327344.html"
},{
         "id": "48286304",
         "tipoPropiedad": "TERRENOS",
         "precioUSD": 200000,
         "fechaUltimaActualizacion": "02-07-2023",
         "terrenoTotal": "30000",
         "terrenoEdificado": -1,
         "cantDormitorios": -1,
         "cantBanos": "1",
         "cantCochera": -1,
         "barrio": "3 HAS - CAMINO 60 CUADRAS - RECIBE MENOR",
         "ciudad": "CORDOBA",
         "URL": "https://www.zonaprop.com.ar/propiedades/3-has-camino-60-cuadras-recibe-menor-48286304.html"
},{
         "id": "48091492",
         "tipoPropiedad": "CASA",
         "precioUSD": 340000,
         "fechaUltimaActualizacion": "25-07-2022",
         "terrenoTotal": "1450",
         "terrenoEdificado": "370",
         "cantDormitorios": "4",
         "cantBanos": "4",
         "cantCochera": "1",
         "barrio": "4 HOJAS",
         "ciudad": "MENDIOLAZA",
         "URL": "https://www.zonaprop.com.ar/propiedades/cuatro-hojas-country-casa-en-venta-48091492.html"
},{
         "id": "48184439",
         "tipoPropiedad": "DEPARTAMENTO",
         "precioUSD": 115000,
         "fechaUltimaActualizacion": "25-07-2022",
         "terrenoTotal": "180",
         "terrenoEdificado": "161",
         "cantDormitorios": "3",
         "cantBanos": "3",
         "cantCochera": -1,
         "barrio": "DOCTA VENTA BAJA DE PRECIO CATEGORIA 3 DORM. 3 BANOS",
         "ciudad": "CORDOBA",
         "URL": "https://www.zonaprop.com.ar/propiedades/docta-venta-baja-de-precio-categoria-3-dorm.-3-banos-48184439.html"
},{
         "id": "47899138",
         "tipoPropiedad": "DEPARTAMENTO",
         "precioUSD": 95000,
         "fechaUltimaActualizacion": "25-07-2022",
         "terrenoTotal": "206",
         "terrenoEdificado": "206",
         "cantDormitorios": "3",
         "cantBanos": "3",
         "cantCochera": -1,
         "barrio": "SAN SALVADOR",
         "ciudad": "CORDOBA",
         "URL": "https://www.zonaprop.com.ar/propiedades/duplex-en-venta-tres-dorm.-con-piscina-apto-bancor-47899138.html"
},{
         "id": "47902969",
         "tipoPropiedad": "TERRENOS",
         "precioUSD": 55000,
         "fechaUltimaActualizacion": "25-07-2022",
         "terrenoTotal": "1000",
         "terrenoEdificado": -1,
         "cantDormitorios": -1,
         "cantBanos": -1,
         "cantCochera": -1,
         "barrio": "LOTES EN VENTA EN LA CERCANIA - BARRIO CERRADO - MENDIOLAZA",
         "ciudad": "MENDIOLAZA",
         "URL": "https://www.zonaprop.com.ar/propiedades/lotes-en-venta-en-la-cercania-barrio-cerrado-47902969.html"
},{
         "id": "47903016",
         "tipoPropiedad": "TERRENOS",
         "precioUSD": 89000,
         "fechaUltimaActualizacion": "25-07-2022",
         "terrenoTotal": "2000",
         "terrenoEdificado": -1,
         "cantDormitorios": -1,
         "cantBanos": -1,
         "cantCochera": -1,
         "barrio": "LAS CORZUELAS",
         "ciudad": "UNQUILLO",
         "URL": "https://www.zonaprop.com.ar/propiedades/lote-en-venta-las-corzuelas-country-2000-m-sup2--etapa-47903016.html"
},{
         "id": "47904825",
         "tipoPropiedad": "DEPARTAMENTO",
         "precioUSD": 63000,
         "fechaUltimaActualizacion": "25-07-2022",
         "terrenoTotal": "70",
         "terrenoEdificado": "70",
         "cantDormitorios": "2",
         "cantBanos": "1",
         "cantCochera": -1,
         "barrio": "PROVIDENCIA",
         "ciudad": "CORDOBA",
         "URL": "https://www.zonaprop.com.ar/propiedades/venta-departamento-2-dorm-barrio-providencia-47904825.html"
},{
         "id": "47906895",
         "tipoPropiedad": "CASA",
         "precioUSD": 198000,
         "fechaUltimaActualizacion": "25-07-2022",
         "terrenoTotal": "260",
         "terrenoEdificado": "185",
         "cantDormitorios": "3",
         "cantBanos": "2",
         "cantCochera": "2",
         "barrio": "VILLA BELGRANO",
         "ciudad": "CORDOBA",
         "URL": "https://www.zonaprop.com.ar/propiedades/hermosa-casa-en-complejo-villa-belgrano-3-dorm-47906895.html"
},{
         "id": "48097653",
         "tipoPropiedad": "DEPARTAMENTO",
         "precioUSD": 33000,
         "fechaUltimaActualizacion": "25-07-2022",
         "terrenoTotal": "40",
         "terrenoEdificado": "40",
         "cantDormitorios": "1",
         "cantBanos": "1",
         "cantCochera": -1,
         "barrio": "ALBERDI",
         "ciudad": "CORDOBA",
         "URL": "https://www.zonaprop.com.ar/propiedades/departamento-venta-alberdi-1-dormitorio-planta-baja.-48097653.html"
}]