[{
         "id": "46664882",
         "tipoPropiedad": "CASA",
         "precioUSD": 395000,
         "fechaUltimaActualizacion": "25-07-2022",
         "terrenoTotal": "1350",
         "terrenoEdificado": "300",
         "cantDormitorios": "3",
         "cantBanos": "3",
         "cantCochera": -1,
         "barrio": "GREENVILLE",
         "ciudad": "CORDOBA",
         "URL": "https://www.zonaprop.com.ar/propiedades/casa-en-venta-greenville-46664882.html"
},{
         "id": "49249576",
         "tipoPropiedad": "DEPARTAMENTO",
         "precioUSD": 185000,
         "fechaUltimaActualizacion": "25-07-2022",
         "terrenoTotal": "121",
         "terrenoEdificado": "88",
         "cantDormitorios": "2",
         "cantBanos": "1",
         "cantCochera": "1",
         "barrio": "VALLE ESCONDIDO",
         "ciudad": "CORDOBA",
         "URL": "https://www.zonaprop.com.ar/propiedades/departamentos-2-dorm.-las-piedras-housing-privado-49249576.html"
},{
         "id": "51861179",
         "tipoPropiedad": "TERRENOS",
         "precioUSD": 72522,
         "fechaUltimaActualizacion": "16-06-2023",
         "terrenoTotal": "4029",
         "terrenoEdificado": -1,
         "cantDormitorios": -1,
         "cantBanos": -1,
         "cantCochera": -1,
         "barrio": "TERRENO EN SAN JAVIER",
         "ciudad": "SAN JAVIER",
         "URL": "https://www.zonaprop.com.ar/propiedades/terreno-en-san-javier-51861179.html"
},{
         "id": "48935193",
         "tipoPropiedad": "DEPARTAMENTO",
         "precioUSD": 105000,
         "fechaUltimaActualizacion": "25-07-2022",
         "terrenoTotal": "86",
         "terrenoEdificado": "76",
         "cantDormitorios": "2",
         "cantBanos": "2",
         "cantCochera": -1,
         "barrio": "GENERAL PAZ",
         "ciudad": "CORDOBA",
         "URL": "https://www.zonaprop.com.ar/propiedades/b-gral-paz-lima-1300-depto-de-2-d-con-2-banos-a-48935193.html"
},{
         "id": "51379519",
         "tipoPropiedad": "CASA",
         "precioUSD": 650000,
         "fechaUltimaActualizacion": "24-03-2023",
         "terrenoTotal": "1200",
         "terrenoEdificado": "320",
         "cantDormitorios": "5",
         "cantBanos": "5",
         "cantCochera": "2",
         "barrio": "ESTANCIA Q2",
         "ciudad": "MENDIOLAZA",
         "URL": "https://www.zonaprop.com.ar/propiedades/country-estancia-q2-mendiolaza-cordoba-51379519.html"
},{
         "id": "50834396",
         "tipoPropiedad": "DEPARTAMENTO",
         "precioUSD": 49000,
         "fechaUltimaActualizacion": "12-12-2022",
         "terrenoTotal": "50",
         "terrenoEdificado": "40",
         "cantDormitorios": "1",
         "cantBanos": "1",
         "cantCochera": -1,
         "barrio": "CENTRO",
         "ciudad": "CORDOBA",
         "URL": "https://www.zonaprop.com.ar/propiedades/departamento-centro-1-dormitorio-cordoba-50834396.html"
},{
         "id": "50661940",
         "tipoPropiedad": "DEPARTAMENTO",
         "precioUSD": 110000,
         "fechaUltimaActualizacion": "10-11-2022",
         "terrenoTotal": "87",
         "terrenoEdificado": "87",
         "cantDormitorios": "2",
         "cantBanos": "2",
         "cantCochera": "1",
         "barrio": "QUEBRADA DE LAS ROSAS",
         "ciudad": "CORDOBA",
         "URL": "https://www.zonaprop.com.ar/propiedades/departamento-en-venta-torre-villasol-vip-50661940.html"
},{
         "id": "51805583",
         "tipoPropiedad": "CASA",
         "precioUSD": 90000,
         "fechaUltimaActualizacion": "08-06-2023",
         "terrenoTotal": "150",
         "terrenoEdificado": "100",
         "cantDormitorios": "3",
         "cantBanos": "1",
         "cantCochera": "1",
         "barrio": "ARGUELLO",
         "ciudad": "CORDOBA",
         "URL": "https://www.zonaprop.com.ar/propiedades/-apto-bancor!-hermoso-duplex-3-dorm.-housing-en-51805583.html"
},{
         "id": "45462252",
         "tipoPropiedad": "CASA",
         "precioUSD": 630000,
         "fechaUltimaActualizacion": "25-07-2022",
         "terrenoTotal": "1976",
         "terrenoEdificado": "340",
         "cantDormitorios": "3",
         "cantBanos": "3",
         "cantCochera": "2",
         "barrio": "EL BOSQUE",
         "ciudad": "CORDOBA",
         "URL": "https://www.zonaprop.com.ar/propiedades/el-bosque-impecable!-45462252.html"
},{
         "id": "50827921",
         "tipoPropiedad": "DEPARTAMENTO",
         "precioUSD": 260000,
         "fechaUltimaActualizacion": "08-12-2022",
         "terrenoTotal": "300",
         "terrenoEdificado": "170",
         "cantDormitorios": "3",
         "cantBanos": "2",
         "cantCochera": "1",
         "barrio": "VILLA BELGRANO",
         "ciudad": "CORDOBA",
         "URL": "https://www.zonaprop.com.ar/propiedades/villa-belgrano-duplex-en-venta-en-barrio-cerrado-50827921.html"
},{
         "id": "50773782",
         "tipoPropiedad": "CASA",
         "precioUSD": 300000,
         "fechaUltimaActualizacion": "28-11-2022",
         "terrenoTotal": "235",
         "terrenoEdificado": "194",
         "cantDormitorios": "3",
         "cantBanos": "2",
         "cantCochera": "2",
         "barrio": "CERRO DE LAS ROSAS",
         "ciudad": "CORDOBA",
         "URL": "https://www.zonaprop.com.ar/propiedades/housing-casa-cerro-de-las-rosas-50773782.html"
},{
         "id": "51293812",
         "tipoPropiedad": "CASA",
         "precioUSD": 173000,
         "fechaUltimaActualizacion": "11-03-2023",
         "terrenoTotal": "180",
         "terrenoEdificado": "180",
         "cantDormitorios": "3",
         "cantBanos": "3",
         "cantCochera": "1",
         "barrio": "LA LUISITA",
         "ciudad": "CORDOBA",
         "URL": "https://www.zonaprop.com.ar/propiedades/duplex-en-venta.-3-dorm.-la-luisita-51293812.html"
},{
         "id": "48619812",
         "tipoPropiedad": "CASA",
         "precioUSD": 170000,
         "fechaUltimaActualizacion": "25-07-2022",
         "terrenoTotal": "195",
         "terrenoEdificado": "170",
         "cantDormitorios": "3",
         "cantBanos": "3",
         "cantCochera": "2",
         "barrio": "GREENVILLE II",
         "ciudad": "CORDOBA",
         "URL": "https://www.zonaprop.com.ar/propiedades/greenville-2-duplex-en-venta-de-3-dorm.-cochera-para-48619812.html"
},{
         "id": "51917355",
         "tipoPropiedad": "TERRENOS",
         "precioUSD": 60000,
         "fechaUltimaActualizacion": "29-06-2023",
         "terrenoTotal": "200",
         "terrenoEdificado": "144",
         "cantDormitorios": "4",
         "cantBanos": "2",
         "cantCochera": "1",
         "barrio": "GUEMES",
         "ciudad": "CORDOBA",
         "URL": "https://www.zonaprop.com.ar/propiedades/se-vende-terreno-de-200-m-sup2--p-inversor-casa-a-51917355.html"
}]