[{
         "id": "2519253",
         "tipoPropiedad": "CASA",
         "precioUSD": 120000,
         "fechaUltimaActualizacion": "21-07-2023",
         "terrenoTotal": 200,
         "terrenoEdificado": 177,
         "cantDormitorios": 3,
         "cantBanos": 3,
         "cantCochera": 1,
         "barrio": "QUINTAS DE SANTA ANA",
         "ciudad": "CORDOBA",
         "URL": "https://clasificados.lavoz.com.ar/avisos/casas/2519253/qtas-sta-ana-27-abril-esq-santa-cruz.html"
},{
         "id": "4802233",
         "tipoPropiedad": "TERRENOS LOTES",
         "precioUSD": 8500,
         "fechaUltimaActualizacion": "21-07-2023",
         "terrenoTotal": 530,
         "terrenoEdificado": -1,
         "cantDormitorios": -1,
         "cantBanos": -1,
         "cantCochera": -1,
         "barrio": "",
         "ciudad": "VILLA CARLOS PAZ",
         "URL": "https://clasificados.lavoz.com.ar/avisos/terrenos-lotes/4802233/lote-jarillas-san-antonio-de-arredondo"
},{
         "id": "2854356",
         "tipoPropiedad": "CASA",
         "precioUSD": 125000,
         "fechaUltimaActualizacion": "21-07-2023",
         "terrenoTotal": 314,
         "terrenoEdificado": 187,
         "cantDormitorios": 3,
         "cantBanos": 3,
         "cantCochera": 2,
         "barrio": "PARQUE CAPITAL SUD",
         "ciudad": "CORDOBA",
         "URL": "https://clasificados.lavoz.com.ar/avisos/casas/2854356/parque-capital-sur-excelente-apta-credito.html"
},{
         "id": "5094534",
         "tipoPropiedad": "CASA",
         "precioUSD": 269000,
         "fechaUltimaActualizacion": "21-07-2023",
         "terrenoTotal": 850,
         "terrenoEdificado": 354,
         "cantDormitorios": 4,
         "cantBanos": -1,
         "cantCochera": -1,
         "barrio": "CERRO DE LAS ROSAS",
         "ciudad": "CORDOBA",
         "URL": "https://clasificados.lavoz.com.ar/avisos/casas/5094534/vende-casa-4-dormitorios-con-pileta-cerro-de-rosas"
},{
         "id": "5094523",
         "tipoPropiedad": "TERRENOS LOTES",
         "precioUSD": 65000,
         "fechaUltimaActualizacion": "21-07-2023",
         "terrenoTotal": 525,
         "terrenoEdificado": -1,
         "cantDormitorios": -1,
         "cantBanos": -1,
         "cantCochera": -1,
         "barrio": "",
         "ciudad": "MALAGUENO",
         "URL": "https://clasificados.lavoz.com.ar/avisos/terrenos-lotes/5094523/vende-lote-525-mts-acquavista"
},{
         "id": "5094525",
         "tipoPropiedad": "DEPARTAMENTO",
         "precioUSD": 87000,
         "fechaUltimaActualizacion": "21-07-2023",
         "terrenoTotal": 65,
         "terrenoEdificado": -1,
         "cantDormitorios": -1,
         "cantBanos": -1,
         "cantCochera": -1,
         "barrio": "CRISOL NORTE",
         "ciudad": "CORDOBA",
         "URL": "https://clasificados.lavoz.com.ar/avisos/departamentos/5094525/vende-departamento-2-dormitorios-pilay-futura"
},{
         "id": "5094526",
         "tipoPropiedad": "CASA",
         "precioUSD": 105000,
         "fechaUltimaActualizacion": "21-07-2023",
         "terrenoTotal": 130,
         "terrenoEdificado": 81,
         "cantDormitorios": 2,
         "cantBanos": -1,
         "cantCochera": -1,
         "barrio": "ALTO VERDE",
         "ciudad": "CORDOBA",
         "URL": "https://clasificados.lavoz.com.ar/avisos/casas/5094526/vende-casa-2-dormitorios-con-cochera-alto-verde-zona-norte"
},{
         "id": "5094544",
         "tipoPropiedad": "CASA",
         "precioUSD": 65000,
         "fechaUltimaActualizacion": "21-07-2023",
         "terrenoTotal": 172,
         "terrenoEdificado": 172,
         "cantDormitorios": 3,
         "cantBanos": 2,
         "cantCochera": 1,
         "barrio": "PUEYRREDON",
         "ciudad": "CORDOBA",
         "URL": "https://clasificados.lavoz.com.ar/avisos/casas/5094544/venta-casa-pa-barrio-pueyrredon-calle-cochabamba-1168"
},{
         "id": "5094521",
         "tipoPropiedad": "TERRENOS LOTES",
         "precioUSD": 20,
         "fechaUltimaActualizacion": "21-07-2023",
         "terrenoTotal": 1000,
         "terrenoEdificado": -1,
         "cantDormitorios": -1,
         "cantBanos": -1,
         "cantCochera": -1,
         "barrio": "VILLA GRAN PARQUE",
         "ciudad": "CORDOBA",
         "URL": "https://clasificados.lavoz.com.ar/avisos/terrenos-lotes/5094521/zona-rancagua-mtrs-paoluccio-esquina-catozzi"
},{
         "id": "5070764",
         "tipoPropiedad": "DUPLEX",
         "precioUSD": 50000,
         "fechaUltimaActualizacion": "21-07-2023",
         "terrenoTotal": 56,
         "terrenoEdificado": 45,
         "cantDormitorios": 1,
         "cantBanos": 2,
         "cantCochera": 1,
         "barrio": "GRANJA DE FUNES",
         "ciudad": "CORDOBA",
         "URL": "https://clasificados.lavoz.com.ar/avisos/casas/5070764/granja-de-funes-1-dorm-apto-credito"
},{
         "id": "5062719",
         "tipoPropiedad": "DEPARTAMENTO",
         "precioUSD": 110000,
         "fechaUltimaActualizacion": "21-07-2023",
         "terrenoTotal": 98,
         "terrenoEdificado": -1,
         "cantDormitorios": 3,
         "cantBanos": 2,
         "cantCochera": -1,
         "barrio": "",
         "ciudad": "VILLA CARLOS PAZ",
         "URL": "https://clasificados.lavoz.com.ar/avisos/departamentos/5062719/venta-duplex-3-dorm-barrio-santa-rita"
},{
         "id": "5062718",
         "tipoPropiedad": "COCHERAS",
         "precioUSD": 10000,
         "fechaUltimaActualizacion": "21-07-2023",
         "terrenoTotal": -1,
         "terrenoEdificado": -1,
         "cantDormitorios": -1,
         "cantBanos": 1,
         "cantCochera": -1,
         "barrio": "CENTRO",
         "ciudad": "CORDOBA",
         "URL": "https://clasificados.lavoz.com.ar/avisos/cocheras/5062718/venta-cochera-en-edificio-argenta-v-b%C2%B0-centro"
},{
         "id": "5094535",
         "tipoPropiedad": "D\u00daPLEX",
         "precioUSD": 69000,
         "fechaUltimaActualizacion": "21-07-2023",
         "terrenoTotal": 57,
         "terrenoEdificado": -1,
         "cantDormitorios": 2,
         "cantBanos": 1,
         "cantCochera": -1,
         "barrio": "",
         "ciudad": "VILLA CARLOS PAZ",
         "URL": "https://clasificados.lavoz.com.ar/avisos/departamentos/5094535/duplex-centrico-villa-carlos-paz"
},{
         "id": "5037218",
         "tipoPropiedad": "DUPLEX",
         "precioUSD": 100000,
         "fechaUltimaActualizacion": "21-07-2023",
         "terrenoTotal": 250,
         "terrenoEdificado": 135,
         "cantDormitorios": 3,
         "cantBanos": 3,
         "cantCochera": 1,
         "barrio": "VILLA ALLENDE PARQUE",
         "ciudad": "CORDOBA",
         "URL": "https://clasificados.lavoz.com.ar/avisos/casas/5037218/excelentes-duplex-a-estrenar"
},{
         "id": "5094519",
         "tipoPropiedad": "TERRENOS LOTES",
         "precioUSD": 6000000,
         "fechaUltimaActualizacion": "21-07-2023",
         "terrenoTotal": 148052,
         "terrenoEdificado": -1,
         "cantDormitorios": -1,
         "cantBanos": -1,
         "cantCochera": -1,
         "barrio": "MIRALTA",
         "ciudad": "CORDOBA",
         "URL": "https://clasificados.lavoz.com.ar/avisos/terrenos-lotes/5094519/vende-terreno-15-hectareas-frente-a-polo-52"
},{
         "id": "5094529",
         "tipoPropiedad": "DEPARTAMENTO",
         "precioUSD": 45000,
         "fechaUltimaActualizacion": "21-07-2023",
         "terrenoTotal": 40,
         "terrenoEdificado": -1,
         "cantDormitorios": 1,
         "cantBanos": -1,
         "cantCochera": -1,
         "barrio": "ALBERDI",
         "ciudad": "CORDOBA",
         "URL": "https://clasificados.lavoz.com.ar/avisos/departamentos/5094529/vende-departamento-1-dormitorio-amoblado-con-balcon-frente-alberdi"
},{
         "id": "5094528",
         "tipoPropiedad": "CASA",
         "precioUSD": 38000,
         "fechaUltimaActualizacion": "21-07-2023",
         "terrenoTotal": 212,
         "terrenoEdificado": 130,
         "cantDormitorios": 3,
         "cantBanos": -1,
         "cantCochera": -1,
         "barrio": "PRIMERO DE MAYO",
         "ciudad": "CORDOBA",
         "URL": "https://clasificados.lavoz.com.ar/avisos/casas/5094528/vendo-casa-b%C2%BA-1ro-de-mayo"
},{
         "id": "5094531",
         "tipoPropiedad": "DEPARTAMENTO",
         "precioUSD": 55000,
         "fechaUltimaActualizacion": "21-07-2023",
         "terrenoTotal": 37,
         "terrenoEdificado": -1,
         "cantDormitorios": 1,
         "cantBanos": -1,
         "cantCochera": -1,
         "barrio": "NUEVA CORDOBA",
         "ciudad": "CORDOBA",
         "URL": "https://clasificados.lavoz.com.ar/avisos/departamentos/5094531/vende-depto-1-dormitorio-balcon-nueva-cordoba"
},{
         "id": "5083951",
         "tipoPropiedad": "CASA",
         "precioUSD": 75000,
         "fechaUltimaActualizacion": "21-07-2023",
         "terrenoTotal": 500,
         "terrenoEdificado": 160,
         "cantDormitorios": 3,
         "cantBanos": 3,
         "cantCochera": -1,
         "barrio": "",
         "ciudad": "CASA GRANDE",
         "URL": "https://clasificados.lavoz.com.ar/avisos/casas/5083951/venta-chalet-valle-de-punilla-3-dorm-casa-grande"
},{
         "id": "4868496",
         "tipoPropiedad": "CASA",
         "precioUSD": 160000,
         "fechaUltimaActualizacion": "21-07-2023",
         "terrenoTotal": 400,
         "terrenoEdificado": 225,
         "cantDormitorios": 4,
         "cantBanos": 3,
         "cantCochera": 1,
         "barrio": "JARDIN",
         "ciudad": "CORDOBA",
         "URL": "https://clasificados.lavoz.com.ar/avisos/casas/4868496/jardin-mejor-zona"
},{
         "id": "5094546",
         "tipoPropiedad": "TERRENOS LOTES",
         "precioUSD": 200000,
         "fechaUltimaActualizacion": "21-07-2023",
         "terrenoTotal": 10600,
         "terrenoEdificado": -1,
         "cantDormitorios": -1,
         "cantBanos": -1,
         "cantCochera": -1,
         "barrio": "",
         "ciudad": "RIO CUARTO",
         "URL": "https://clasificados.lavoz.com.ar/avisos/terrenos-lotes/5094546/en-venta-terreno-de-10600-m2"
}]