[{
         "id": "50207626",
         "tipoPropiedad": "DEPARTAMENTO",
         "precioUSD": 39000,
         "fechaUltimaActualizacion": "26-08-2022",
         "vendedor": "INMOBILIARIA",
         "terrenoTotal": 50.0,
         "terrenoEdificado": 50.0,
         "cantDormitorios": 1.0,
         "cantBanos": 1.0,
         "cantCochera": -1,
         "barrio": "ALBERDI",
         "ciudad": "CORDOBA",
         "coordX": -31.4045513,
         "coordY": -64.2142082,
         "activo": false,
         "URL": "https://www.zonaprop.com.ar/propiedades/venta-departamento-1-dormitorio-barrio-alberdi-50207626.html"
},{
         "id": "45972235",
         "tipoPropiedad": "DEPARTAMENTO",
         "precioUSD": 45000,
         "fechaUltimaActualizacion": "04-08-2022",
         "vendedor": "INMOBILIARIA",
         "terrenoTotal": 55.0,
         "terrenoEdificado": 45.0,
         "cantDormitorios": 1.0,
         "cantBanos": 1.0,
         "cantCochera": -1,
         "barrio": "ALBERDI",
         "ciudad": "CORDOBA",
         "coordX": -31.4050761,
         "coordY": -64.1971299,
         "activo": false,
         "URL": "https://www.zonaprop.com.ar/propiedades/departamento-en-venta-de-1-dormitorio-en-edificio-45972235.html"
},{
         "id": "52002635",
         "tipoPropiedad": "DEPARTAMENTO",
         "precioUSD": 80000,
         "fechaUltimaActualizacion": "14-07-2023",
         "vendedor": "INMOBILIARIA",
         "terrenoTotal": 60.0,
         "terrenoEdificado": 60.0,
         "cantDormitorios": 1.0,
         "cantBanos": 2.0,
         "cantCochera": -1,
         "barrio": "MILENICA SAGRADA FAMILIA - 1 DORM - APTO CREDITO",
         "ciudad": "CORDOBA",
         "coordX": -31.395861,
         "coordY": -64.2312597,
         "activo": true,
         "URL": "https://www.zonaprop.com.ar/propiedades/milenica-sagrada-familia-1-dorm-apto-credito-52002635.html"
},{
         "id": "48451743",
         "tipoPropiedad": "DEPARTAMENTO",
         "precioUSD": 40000,
         "fechaUltimaActualizacion": "04-08-2022",
         "vendedor": "INMOBILIARIA",
         "terrenoTotal": 45.0,
         "terrenoEdificado": 45.0,
         "cantDormitorios": 1.0,
         "cantBanos": 1.0,
         "cantCochera": -1,
         "barrio": "SAN MARTIN",
         "ciudad": "CORDOBA",
         "coordX": -31.3866214123,
         "coordY": -64.2005322033,
         "activo": false,
         "URL": "https://www.zonaprop.com.ar/propiedades/departamento-san-martin-48451743.html"
},{
         "id": "49312344",
         "tipoPropiedad": "DEPARTAMENTO",
         "precioUSD": 90000,
         "fechaUltimaActualizacion": "04-08-2022",
         "vendedor": "INMOBILIARIA",
         "terrenoTotal": 56.0,
         "terrenoEdificado": 48.0,
         "cantDormitorios": 1.0,
         "cantBanos": 1.0,
         "cantCochera": 1.0,
         "barrio": "CENTRO",
         "ciudad": "VILLA CARLOS PAZ",
         "coordX": -31.419672670048378,
         "coordY": -64.50310652593382,
         "activo": false,
         "URL": "https://www.zonaprop.com.ar/propiedades/departamento-a-estrenar-a-50-m-de-la-peatonal-49312344.html"
},{
         "id": "50985042",
         "tipoPropiedad": "PH",
         "precioUSD": 39000,
         "fechaUltimaActualizacion": "14-01-2023",
         "vendedor": "INMOBILIARIA",
         "terrenoTotal": 100.0,
         "terrenoEdificado": 75.0,
         "cantDormitorios": 2.0,
         "cantBanos": 2.0,
         "cantCochera": 1.0,
         "barrio": "VALLE CERCANO",
         "ciudad": "CORDOBA",
         "coordX": -33.1768837,
         "coordY": -64.99436951,
         "activo": false,
         "URL": "https://www.zonaprop.com.ar/propiedades/liquidacion!-duplex-a-estrenar!-u$s39.000.-50985042.html"
},{
         "id": "51531014",
         "tipoPropiedad": "DEPARTAMENTO",
         "precioUSD": 67000,
         "fechaUltimaActualizacion": "23-04-2023",
         "vendedor": "INMOBILIARIA",
         "terrenoTotal": 55.0,
         "terrenoEdificado": 45.0,
         "cantDormitorios": 1.0,
         "cantBanos": 1.0,
         "cantCochera": -1,
         "barrio": "NUEVA CORDOBA",
         "ciudad": "CORDOBA",
         "coordX": -31.4233869,
         "coordY": -64.1903616,
         "activo": false,
         "URL": "https://www.zonaprop.com.ar/propiedades/facilidad-de-pago-a-estrenar-en-nueva-cordoba-51531014.html"
},{
         "id": "52054997",
         "tipoPropiedad": "DEPARTAMENTO",
         "precioUSD": 69000,
         "fechaUltimaActualizacion": "26-07-2023",
         "vendedor": "PARTICULAR",
         "terrenoTotal": 88.0,
         "terrenoEdificado": 73.0,
         "cantDormitorios": 2.0,
         "cantBanos": 1.0,
         "cantCochera": -1,
         "barrio": "CENTRO",
         "ciudad": "CORDOBA",
         "coordX": -31.4089066,
         "coordY": -64.1782935,
         "activo": true,
         "URL": "https://www.zonaprop.com.ar/propiedades/vendo-apto-bancor-departamento-2-dorm.-en-barrio-52054997.html"
},{
         "id": "51677778",
         "tipoPropiedad": "DEPARTAMENTO",
         "precioUSD": 69000,
         "fechaUltimaActualizacion": "17-05-2023",
         "vendedor": "INMOBILIARIA",
         "terrenoTotal": 38.0,
         "terrenoEdificado": 38.0,
         "cantDormitorios": 1.0,
         "cantBanos": 1.0,
         "cantCochera": -1,
         "barrio": "NUEVA CORDOBA",
         "ciudad": "CORDOBA",
         "coordX": -31.4264728,
         "coordY": -64.1912424,
         "activo": false,
         "URL": "https://www.zonaprop.com.ar/propiedades/vendo-dpto-1-dorm-c-balcon.-nueva-cordoba.-51677778.html"
},{
         "id": "51619651",
         "tipoPropiedad": "CASA",
         "precioUSD": 65000,
         "fechaUltimaActualizacion": "06-05-2023",
         "vendedor": "INMOBILIARIA",
         "terrenoTotal": 450.0,
         "terrenoEdificado": 58.0,
         "cantDormitorios": 2.0,
         "cantBanos": 1.0,
         "cantCochera": 1.0,
         "barrio": "CASA EN VENTA DE 2 DORM. C/ COCHERA EN VALLE HERMOSO",
         "ciudad": "VALLE HERMOSO",
         "coordX": -31.1175686142764,
         "coordY": -64.4794283697368,
         "activo": false,
         "URL": "https://www.zonaprop.com.ar/propiedades/casa-en-venta-de-2-dorm.-c-cochera-en-valle-hermoso-51619651.html"
},{
         "id": "51402167",
         "tipoPropiedad": "DEPARTAMENTO",
         "precioUSD": 42000,
         "fechaUltimaActualizacion": "30-03-2023",
         "vendedor": "INMOBILIARIA",
         "terrenoTotal": 45.0,
         "terrenoEdificado": 45.0,
         "cantDormitorios": -1,
         "cantBanos": 1.0,
         "cantCochera": -1,
         "barrio": "NUEVA CORDOBA",
         "ciudad": "CORDOBA",
         "coordX": -31.4238992,
         "coordY": -64.17580579999999,
         "activo": false,
         "URL": "https://www.zonaprop.com.ar/propiedades/venta-de-excelente-monoambiente-en-nueva-cordoba!-51402167.html"
},{
         "id": "51849159",
         "tipoPropiedad": "DEPARTAMENTO",
         "precioUSD": 65000,
         "fechaUltimaActualizacion": "14-06-2023",
         "vendedor": "INMOBILIARIA",
         "terrenoTotal": 45.0,
         "terrenoEdificado": 45.0,
         "cantDormitorios": 2.0,
         "cantBanos": -1,
         "cantCochera": -1,
         "barrio": "ALTO ALBERDI",
         "ciudad": "CORDOBA",
         "coordX": -31.4029818,
         "coordY": -64.2183352,
         "activo": false,
         "URL": "https://www.zonaprop.com.ar/propiedades/venta-departamento-con-patio-1-dorm-alto-alberdi-51849159.html"
},{
         "id": "51881493",
         "tipoPropiedad": "DEPARTAMENTO",
         "precioUSD": 49999,
         "fechaUltimaActualizacion": "22-06-2023",
         "vendedor": "INMOBILIARIA",
         "terrenoTotal": 57.0,
         "terrenoEdificado": 57.0,
         "cantDormitorios": 1.0,
         "cantBanos": 1.0,
         "cantCochera": -1,
         "barrio": "CENTRO",
         "ciudad": "CORDOBA",
         "coordX": -31.4196648,
         "coordY": -64.1848073,
         "activo": true,
         "URL": "https://www.zonaprop.com.ar/propiedades/venta-departamento-1-dormitorio-centro!-51881493.html"
},{
         "id": "51232191",
         "tipoPropiedad": "DEPARTAMENTO",
         "precioUSD": 62000,
         "fechaUltimaActualizacion": "01-03-2023",
         "vendedor": "INMOBILIARIA",
         "terrenoTotal": 48.0,
         "terrenoEdificado": 48.0,
         "cantDormitorios": 1.0,
         "cantBanos": 1.0,
         "cantCochera": -1,
         "barrio": "GUEMES",
         "ciudad": "CORDOBA",
         "coordX": -31.4260144,
         "coordY": -64.1940367,
         "activo": false,
         "URL": "https://www.zonaprop.com.ar/propiedades/venta-1-dormitorio-marcelo-t.-de-alvear-1000-51232191.html"
},{
         "id": "52053456",
         "tipoPropiedad": "DEPARTAMENTO",
         "precioUSD": 70000,
         "fechaUltimaActualizacion": "25-07-2023",
         "vendedor": "INMOBILIARIA",
         "terrenoTotal": 52.0,
         "terrenoEdificado": 45.0,
         "cantDormitorios": -1,
         "cantBanos": 1.0,
         "cantCochera": 1.0,
         "barrio": "VILLA DOMINGUEZ",
         "ciudad": "VILLA CARLOS PAZ",
         "coordX": -31.410758,
         "coordY": -64.494171,
         "activo": true,
         "URL": "https://www.zonaprop.com.ar/propiedades/villa-carlos-paz-departamento-de-1-dormitorio-en-venta-52053456.html"
},{
         "id": "49811475",
         "tipoPropiedad": "DEPARTAMENTO",
         "precioUSD": 45000,
         "fechaUltimaActualizacion": "04-08-2022",
         "vendedor": "INMOBILIARIA",
         "terrenoTotal": 49.0,
         "terrenoEdificado": 49.0,
         "cantDormitorios": 2.0,
         "cantBanos": 1.0,
         "cantCochera": -1,
         "barrio": "SAN VICENTE",
         "ciudad": "CORDOBA",
         "coordX": -31.425326372,
         "coordY": -64.1379659349,
         "activo": false,
         "URL": "https://www.zonaprop.com.ar/propiedades/departamento-san-vicente-49811475.html"
},{
         "id": "51956513",
         "tipoPropiedad": "DEPARTAMENTO",
         "precioUSD": 65000,
         "fechaUltimaActualizacion": "07-07-2023",
         "vendedor": "INMOBILIARIA",
         "terrenoTotal": 45.0,
         "terrenoEdificado": 45.0,
         "cantDormitorios": 1.0,
         "cantBanos": 1.0,
         "cantCochera": 1.0,
         "barrio": "CENTRO",
         "ciudad": "VILLA CARLOS PAZ",
         "coordX": -31.4239998,
         "coordY": -64.4993179,
         "activo": true,
         "URL": "https://www.zonaprop.com.ar/propiedades/departamento-un-dormitorio-cochera-pileta.-centro-51956513.html"
},{
         "id": "51598423",
         "tipoPropiedad": "DEPARTAMENTO",
         "precioUSD": 32000,
         "fechaUltimaActualizacion": "04-05-2023",
         "vendedor": "INMOBILIARIA",
         "terrenoTotal": -1,
         "terrenoEdificado": 39.0,
         "cantDormitorios": 1.0,
         "cantBanos": 1.0,
         "cantCochera": -1,
         "barrio": "CENTRO",
         "ciudad": "CORDOBA",
         "coordX": -31.4165378,
         "coordY": -64.1982932,
         "activo": false,
         "URL": "https://www.zonaprop.com.ar/propiedades/liquido-departamento-de-1dorm-centro-51598423.html"
},{
         "id": "52024888",
         "tipoPropiedad": "DEPARTAMENTO",
         "precioUSD": 45000,
         "fechaUltimaActualizacion": "19-07-2023",
         "vendedor": "INMOBILIARIA",
         "terrenoTotal": 38.0,
         "terrenoEdificado": 38.0,
         "cantDormitorios": 2.0,
         "cantBanos": 1.0,
         "cantCochera": -1,
         "barrio": "CENTRO",
         "ciudad": "CORDOBA",
         "coordX": -31.4142026,
         "coordY": -64.18780079999999,
         "activo": true,
         "URL": "https://www.zonaprop.com.ar/propiedades/centro-2-dorm.-ideal-temporario-52024888.html"
}]