[{
         "id": "50754515",
         "tipoPropiedad": "CASA",
         "precioUSD": 650000,
         "fechaUltimaActualizacion": "27-11-2022",
         "vendedor": "INMOBILIARIA",
         "terrenoTotal": 1590.0,
         "terrenoEdificado": 611.0,
         "cantDormitorios": 5.0,
         "cantBanos": 4.0,
         "cantCochera": 4.0,
         "barrio": "ESPECTACULAR CASA EN EL BOSQUE",
         "ciudad": "CORDOBA",
         "coordX": -31.3465511,
         "coordY": -64.3055671,
         "activo": false,
         "URL": "https://www.zonaprop.com.ar/propiedades/espectacular-casa-en-el-bosque-50754515.html"
},{
         "id": "51470358",
         "tipoPropiedad": "TERRENOS",
         "precioUSD": 2000000,
         "fechaUltimaActualizacion": "13-04-2023",
         "vendedor": "INMOBILIARIA",
         "terrenoTotal": 1743.0,
         "terrenoEdificado": 1743.0,
         "cantDormitorios": -1,
         "cantBanos": -1,
         "cantCochera": -1,
         "barrio": "LAS FLORES",
         "ciudad": "CORDOBA",
         "coordX": -31.4460491,
         "coordY": -64.1982141,
         "activo": false,
         "URL": "https://www.zonaprop.com.ar/propiedades/venta-terreno-1800-m-sobre-av-velez-sarsfield-51470358.html"
},{
         "id": "51659347",
         "tipoPropiedad": "TERRENOS",
         "precioUSD": 145000,
         "fechaUltimaActualizacion": "13-05-2023",
         "vendedor": "INMOBILIARIA",
         "terrenoTotal": 1250.0,
         "terrenoEdificado": 1249.0,
         "cantDormitorios": -1,
         "cantBanos": -1,
         "cantCochera": -1,
         "barrio": "ESTANCIA Q2",
         "ciudad": "MENDIOLAZA",
         "coordX": -31.2650699,
         "coordY": -64.3205565,
         "activo": false,
         "URL": "https://www.zonaprop.com.ar/propiedades/nuevo-terreno-en-estancia-q2-mendiolaza-de-1250-51659347.html"
},{
         "id": "50481936",
         "tipoPropiedad": "CASA",
         "precioUSD": 1600000,
         "fechaUltimaActualizacion": "15-10-2022",
         "vendedor": "INMOBILIARIA",
         "terrenoTotal": 4774.0,
         "terrenoEdificado": 850.0,
         "cantDormitorios": 8.0,
         "cantBanos": 8.0,
         "cantCochera": 8.0,
         "barrio": "VENTA DE COMPLEJO DE CABANAS - CAB0063",
         "ciudad": "VILLA GENERAL BELGRANO",
         "coordX": -31.971501606670007,
         "coordY": -64.552294816008,
         "activo": false,
         "URL": "https://www.zonaprop.com.ar/propiedades/venta-de-complejo-de-cabanas-cab0063-50481936.html"
},{
         "id": "51880060",
         "tipoPropiedad": "TERRENOS",
         "precioUSD": 85000,
         "fechaUltimaActualizacion": "21-06-2023",
         "vendedor": "INMOBILIARIA",
         "terrenoTotal": 1500.0,
         "terrenoEdificado": 1400.0,
         "cantDormitorios": -1,
         "cantBanos": -1,
         "cantCochera": -1,
         "barrio": "LA DESEADA COUNTRY",
         "ciudad": "LA CALERA",
         "coordX": -31.35559499999999,
         "coordY": -64.3227122,
         "activo": true,
         "URL": "https://www.zonaprop.com.ar/propiedades/la-deseada-1500-m-apto-duplex-51880060.html"
},{
         "id": "51449053",
         "tipoPropiedad": "TERRENOS",
         "precioUSD": 130000,
         "fechaUltimaActualizacion": "07-04-2023",
         "vendedor": "INMOBILIARIA",
         "terrenoTotal": 1340.0,
         "terrenoEdificado": 1339.0,
         "cantDormitorios": -1,
         "cantBanos": -1,
         "cantCochera": -1,
         "barrio": "ESTANCIA EL TERRON",
         "ciudad": "MENDIOLAZA",
         "coordX": -31.2595068,
         "coordY": -64.3001609,
         "activo": false,
         "URL": "https://www.zonaprop.com.ar/propiedades/estancia-el-terron-lote-de-1340-m-sup2-51449053.html"
},{
         "id": "41948747",
         "tipoPropiedad": "CASA",
         "precioUSD": 380000,
         "fechaUltimaActualizacion": "05-08-2022",
         "vendedor": "INMOBILIARIA",
         "terrenoTotal": 30000.0,
         "terrenoEdificado": 950.0,
         "cantDormitorios": 8.0,
         "cantBanos": 8.0,
         "cantCochera": -1,
         "barrio": "CASA GRANDE VENTA CASA 8 D. C - TERRENO 3 HAS",
         "ciudad": "CASA GRANDE",
         "coordX": -31.1681504,
         "coordY": -64.4759963,
         "activo": false,
         "URL": "https://www.zonaprop.com.ar/propiedades/casa-grande-venta-casa-8-d.-c-terreno-3-has-41948747.html"
},{
         "id": "51555203",
         "tipoPropiedad": "TERRENOS",
         "precioUSD": 176000,
         "fechaUltimaActualizacion": "27-04-2023",
         "vendedor": "INMOBILIARIA",
         "terrenoTotal": 1433.0,
         "terrenoEdificado": 1432.0,
         "cantDormitorios": -1,
         "cantBanos": -1,
         "cantCochera": -1,
         "barrio": "ESTANCIA Q2",
         "ciudad": "MENDIOLAZA",
         "coordX": -31.2673667,
         "coordY": -64.30559549999998,
         "activo": false,
         "URL": "https://www.zonaprop.com.ar/propiedades/nuevo-terreno-en-estancia-q2-mendiolaza-de-1433-51555203.html"
},{
         "id": "48837297",
         "tipoPropiedad": "CASA",
         "precioUSD": 150000,
         "fechaUltimaActualizacion": "05-08-2022",
         "vendedor": "INMOBILIARIA",
         "terrenoTotal": 1700.0,
         "terrenoEdificado": 650.0,
         "cantDormitorios": 3.0,
         "cantBanos": 2.0,
         "cantCochera": -1,
         "barrio": "LAS FLORES",
         "ciudad": "CORDOBA",
         "coordX": -31.4538073,
         "coordY": -64.1954725,
         "activo": false,
         "URL": "https://www.zonaprop.com.ar/propiedades/buenos-m-de-terreno-ideal-inversion-para-institucion-48837297.html"
},{
         "id": "49718634",
         "tipoPropiedad": "TERRENOS",
         "precioUSD": 9800,
         "fechaUltimaActualizacion": "05-08-2022",
         "vendedor": "INMOBILIARIA",
         "terrenoTotal": 602.0,
         "terrenoEdificado": 602.0,
         "cantDormitorios": -1,
         "cantBanos": -1,
         "cantCochera": -1,
         "barrio": "OTROS",
         "ciudad": "AGUA DE ORO",
         "coordX": -31.0598091,
         "coordY": -64.2927653,
         "activo": false,
         "URL": "https://www.zonaprop.com.ar/propiedades/venta-lote-agua-de-oro.-con-escritura-49718634.html"
},{
         "id": "51458680",
         "tipoPropiedad": "TERRENOS",
         "precioUSD": 255000,
         "fechaUltimaActualizacion": "11-04-2023",
         "vendedor": "INMOBILIARIA",
         "terrenoTotal": 1737.0,
         "terrenoEdificado": 1736.0,
         "cantDormitorios": -1,
         "cantBanos": -1,
         "cantCochera": -1,
         "barrio": "ESTANCIA EL TERRON",
         "ciudad": "MENDIOLAZA",
         "coordX": -31.2595068,
         "coordY": -64.3001609,
         "activo": false,
         "URL": "https://www.zonaprop.com.ar/propiedades/estancia-el-terron-lote-fondo-golf-de-1737-m-sup2-51458680.html"
},{
         "id": "47005041",
         "tipoPropiedad": "TERRENOS",
         "precioUSD": 36750,
         "fechaUltimaActualizacion": "05-08-2022",
         "vendedor": "INMOBILIARIA",
         "terrenoTotal": 700.0,
         "terrenoEdificado": 700.0,
         "cantDormitorios": -1,
         "cantBanos": -1,
         "cantCochera": -1,
         "barrio": "BELA VISTA",
         "ciudad": "RIO CEBALLOS",
         "coordX": -31.199935842628733,
         "coordY": -64.286246,
         "activo": false,
         "URL": "https://www.zonaprop.com.ar/propiedades/lotes-en-bela-vista-sobre-e-53-47005041.html"
},{
         "id": "45273445",
         "tipoPropiedad": "TERRENOS",
         "precioUSD": 165000,
         "fechaUltimaActualizacion": "05-08-2022",
         "vendedor": "INMOBILIARIA",
         "terrenoTotal": 1500.0,
         "terrenoEdificado": 1500.0,
         "cantDormitorios": -1,
         "cantBanos": -1,
         "cantCochera": -1,
         "barrio": "SIETE SOLES NATURALEZA URBANA",
         "ciudad": "CORDOBA",
         "coordX": -31.4391831,
         "coordY": -64.3029528,
         "activo": false,
         "URL": "https://www.zonaprop.com.ar/propiedades/lote-en-heredades-siete-soles-1500-m-sup2-45273445.html"
},{
         "id": "47968031",
         "tipoPropiedad": "TERRENOS",
         "precioUSD": 60000,
         "fechaUltimaActualizacion": "05-08-2022",
         "vendedor": "INMOBILIARIA",
         "terrenoTotal": 1450.0,
         "terrenoEdificado": 1450.0,
         "cantDormitorios": -1,
         "cantBanos": -1,
         "cantCochera": -1,
         "barrio": "MALAGUENO",
         "ciudad": "MALAGUENO",
         "coordX": -31.4428897,
         "coordY": -64.4388196,
         "activo": false,
         "URL": "https://www.zonaprop.com.ar/propiedades/barrio-privado-la-arbolada-autopista-cordoba-carlos-47968031.html"
},{
         "id": "50931188",
         "tipoPropiedad": "TERRENOS",
         "precioUSD": 32000,
         "fechaUltimaActualizacion": "03-01-2023",
         "vendedor": "INMOBILIARIA",
         "terrenoTotal": 750.0,
         "terrenoEdificado": 750.0,
         "cantDormitorios": -1,
         "cantBanos": -1,
         "cantCochera": -1,
         "barrio": "NUEVO RIO CEBALLOS",
         "ciudad": "RIO CEBALLOS",
         "coordX": -31.1737267,
         "coordY": -64.31233259999999,
         "activo": false,
         "URL": "https://www.zonaprop.com.ar/propiedades/terreno-nuevo-rio-ceballos-50931188.html"
},{
         "id": "50934534",
         "tipoPropiedad": "CASA",
         "precioUSD": 179900,
         "fechaUltimaActualizacion": "04-01-2023",
         "vendedor": "INMOBILIARIA",
         "terrenoTotal": 231.33,
         "terrenoEdificado": 182.0,
         "cantDormitorios": 3.0,
         "cantBanos": 3.0,
         "cantCochera": 2.0,
         "barrio": "ARGUELLO",
         "ciudad": "CORDOBA",
         "coordX": -31.34229088,
         "coordY": -64.25602722,
         "activo": false,
         "URL": "https://www.zonaprop.com.ar/propiedades/vendo-duplex-3-dorm.-barrio-arguello-housing-spano-50934534.html"
},{
         "id": "46941724",
         "tipoPropiedad": "TERRENOS",
         "precioUSD": 160000,
         "fechaUltimaActualizacion": "05-08-2022",
         "vendedor": "INMOBILIARIA",
         "terrenoTotal": 750.0,
         "terrenoEdificado": 750.0,
         "cantDormitorios": -1,
         "cantBanos": -1,
         "cantCochera": -1,
         "barrio": "SAN ALFONSO",
         "ciudad": "VILLA ALLENDE",
         "coordX": -31.3072544,
         "coordY": -64.28817450000001,
         "activo": false,
         "URL": "https://www.zonaprop.com.ar/propiedades/v.-allende-atencion-desarrollistas-y-constructores-46941724.html"
}]