[{
         "id": "48983382",
         "tipoPropiedad": "TERRENOS",
         "precioUSD": 9500,
         "fechaUltimaActualizacion": "01-08-2022",
         "vendedor": "INMOBILIARIA",
         "terrenoTotal": "350",
         "terrenoEdificado": -1,
         "cantDormitorios": -1,
         "cantBanos": -1,
         "cantCochera": -1,
         "barrio": "VENTA TERRENO ALTOS DE LA COLONIA COLONIA TIROLESA",
         "ciudad": "COLONIA TIROLESA",
         "coordX": -31.2377187,
         "coordY": -64.0672701,
         "activo": false,
         "URL": "https://www.zonaprop.com.ar/propiedades/venta-terreno-altos-de-la-colonia-colonia-tirolesa-48983382.html"
},{
         "id": "48983479",
         "tipoPropiedad": "TERRENOS",
         "precioUSD": 185000,
         "fechaUltimaActualizacion": "01-08-2022",
         "vendedor": "INMOBILIARIA",
         "terrenoTotal": "190",
         "terrenoEdificado": "340",
         "cantDormitorios": -1,
         "cantBanos": "4",
         "cantCochera": -1,
         "barrio": "CENTRO",
         "ciudad": "CORDOBA",
         "coordX": -31.4194861,
         "coordY": -64.1768448999999,
         "activo": false,
         "URL": "https://www.zonaprop.com.ar/propiedades/vendo-lote-en-el-centro-apto-desarrollo-buen-48983479.html"
},{
         "id": "48535278",
         "tipoPropiedad": "TERRENOS",
         "precioUSD": 900000,
         "fechaUltimaActualizacion": "01-08-2022",
         "vendedor": "INMOBILIARIA",
         "terrenoTotal": "110000",
         "terrenoEdificado": "500",
         "cantDormitorios": "3",
         "cantBanos": "1",
         "cantCochera": -1,
         "barrio": "SE VENDE HAS, FRACCION, CASONA EN SAN ANTONIO DE ARREDONDO",
         "ciudad": "VILLA CARLOS PAZ",
         "coordX": -31.46863363679593,
         "coordY": -64.5158618,
         "activo": false,
         "URL": "https://www.zonaprop.com.ar/propiedades/se-vende-has-fraccion-casona-en-san-antonio-de-48535278.html"
},{
         "id": "48940550",
         "tipoPropiedad": "DEPARTAMENTO",
         "precioUSD": 190000,
         "fechaUltimaActualizacion": "01-08-2022",
         "vendedor": "INMOBILIARIA",
         "terrenoTotal": "180",
         "terrenoEdificado": "170",
         "cantDormitorios": "3",
         "cantBanos": "3",
         "cantCochera": -1,
         "barrio": "GREENVILLE II",
         "ciudad": "CORDOBA",
         "coordX": -31.4842449,
         "coordY": -64.1689224,
         "activo": false,
         "URL": "https://www.zonaprop.com.ar/propiedades/duplex-de-3-dorm.-a-estrenar-greenville-2-categoria-48940550.html"
},{
         "id": "48940595",
         "tipoPropiedad": "CASA",
         "precioUSD": 150000,
         "fechaUltimaActualizacion": "01-08-2022",
         "vendedor": "INMOBILIARIA",
         "terrenoTotal": "330",
         "terrenoEdificado": "225",
         "cantDormitorios": "4",
         "cantBanos": "3",
         "cantCochera": -1,
         "barrio": "PASO DE LOS ANDES",
         "ciudad": "CORDOBA",
         "coordX": -31.4159886,
         "coordY": -64.2026992,
         "activo": false,
         "URL": "https://www.zonaprop.com.ar/propiedades/gran-casa-a-la-venta-a-m-del-shopping-excelente-48940595.html"
},{
         "id": "49007048",
         "tipoPropiedad": "DEPARTAMENTO",
         "precioUSD": 1400000,
         "fechaUltimaActualizacion": "01-08-2022",
         "vendedor": "INMOBILIARIA",
         "terrenoTotal": "1400",
         "terrenoEdificado": "1000",
         "cantDormitorios": "3",
         "cantBanos": "5",
         "cantCochera": "3",
         "barrio": "LA RUFINA",
         "ciudad": "LA CALERA",
         "coordX": -31.3496772,
         "coordY": -64.3104833,
         "activo": false,
         "URL": "https://www.zonaprop.com.ar/propiedades/exclusiva-casa-en-la-rufina-3-dorm.-49007048.html"
},{
         "id": "49353743",
         "tipoPropiedad": "DEPARTAMENTO",
         "precioUSD": 40000,
         "fechaUltimaActualizacion": "01-08-2022",
         "vendedor": "INMOBILIARIA",
         "terrenoTotal": "44",
         "terrenoEdificado": "44",
         "cantDormitorios": "1",
         "cantBanos": "1",
         "cantCochera": -1,
         "barrio": "DPTO 1 DORMITORIO! ESCUCHO OFERTAS!",
         "ciudad": "RIO CUARTO",
         "coordX": -33.1286561,
         "coordY": -64.3460885,
         "activo": false,
         "URL": "https://www.zonaprop.com.ar/propiedades/dpto-1-dormitorio!-escucho-ofertas!-49353743.html"
},{
         "id": "49036423",
         "tipoPropiedad": "DEPARTAMENTO",
         "precioUSD": 71500,
         "fechaUltimaActualizacion": "01-08-2022",
         "vendedor": "INMOBILIARIA",
         "terrenoTotal": "58",
         "terrenoEdificado": -1,
         "cantDormitorios": "2",
         "cantBanos": "1",
         "cantCochera": -1,
         "barrio": "ALBERDI",
         "ciudad": "CORDOBA",
         "coordX": -31.4075039,
         "coordY": -64.2030746,
         "activo": false,
         "URL": "https://www.zonaprop.com.ar/propiedades/departamento-de-2-dormitorio-en-barrio-alberdi-49036423.html"
},{
         "id": "49039684",
         "tipoPropiedad": "CASA",
         "precioUSD": 40000,
         "fechaUltimaActualizacion": "01-08-2022",
         "vendedor": "INMOBILIARIA",
         "terrenoTotal": "270",
         "terrenoEdificado": "174",
         "cantDormitorios": "3",
         "cantBanos": "2",
         "cantCochera": "1",
         "barrio": "VENTA CASA 3 DORM. CALIFORNIA Z. SUR CORDOBA",
         "ciudad": "CORDOBA",
         "coordX": -31.451268192243,
         "coordY": -64.204224944115,
         "activo": false,
         "URL": "https://www.zonaprop.com.ar/propiedades/venta-casa-3-dorm.-california-z.-sur-cordoba-49039684.html"
},{
         "id": "49134892",
         "tipoPropiedad": "DEPARTAMENTO",
         "precioUSD": 80000,
         "fechaUltimaActualizacion": "01-08-2022",
         "vendedor": "INMOBILIARIA",
         "terrenoTotal": "60",
         "terrenoEdificado": "60",
         "cantDormitorios": "1",
         "cantBanos": "1",
         "cantCochera": -1,
         "barrio": "NUEVA CORDOBA",
         "ciudad": "CORDOBA",
         "coordX": -31.4219355,
         "coordY": -64.184932,
         "activo": false,
         "URL": "https://www.zonaprop.com.ar/propiedades/a-estrenar-depto-1-dorm-mas-escritorio-a-m-del-buen-49134892.html"
},{
         "id": "48775917",
         "tipoPropiedad": "TERRENOS",
         "precioUSD": 18500,
         "fechaUltimaActualizacion": "01-08-2022",
         "vendedor": "INMOBILIARIA",
         "terrenoTotal": "250",
         "terrenoEdificado": -1,
         "cantDormitorios": -1,
         "cantBanos": -1,
         "cantCochera": -1,
         "barrio": "VALLE CERCANO",
         "ciudad": "CORDOBA",
         "coordX": -31.48529816,
         "coordY": -64.22406769,
         "activo": false,
         "URL": "https://www.zonaprop.com.ar/propiedades/lote-b-valle-cercano-48775917.html"
},{
         "id": "48738832",
         "tipoPropiedad": "DEPARTAMENTO",
         "precioUSD": 130000,
         "fechaUltimaActualizacion": "01-08-2022",
         "vendedor": "INMOBILIARIA",
         "terrenoTotal": "180",
         "terrenoEdificado": "115",
         "cantDormitorios": "3",
         "cantBanos": "2",
         "cantCochera": -1,
         "barrio": "NUEVO POETA LUGONES",
         "ciudad": "CORDOBA",
         "coordX": -31.3562758,
         "coordY": -64.2159262,
         "activo": false,
         "URL": "https://www.zonaprop.com.ar/propiedades/nuevo-poeta-lugones!-venta-duplex-3-dorm-con-amplio-48738832.html"
},{
         "id": "49252530",
         "tipoPropiedad": "DEPARTAMENTO",
         "precioUSD": 56000,
         "fechaUltimaActualizacion": "01-08-2022",
         "vendedor": "INMOBILIARIA",
         "terrenoTotal": "52",
         "terrenoEdificado": "49",
         "cantDormitorios": "1",
         "cantBanos": "1",
         "cantCochera": -1,
         "barrio": "GENERAL PAZ",
         "ciudad": "CORDOBA",
         "coordX": -31.4127357,
         "coordY": -64.1623683,
         "activo": false,
         "URL": "https://www.zonaprop.com.ar/propiedades/departamento-general-paz-1-dormitorio-con-balcon-a-49252530.html"
},{
         "id": "50823412",
         "tipoPropiedad": "CASA",
         "precioUSD": 49500,
         "fechaUltimaActualizacion": "07-12-2022",
         "vendedor": "INMOBILIARIA",
         "terrenoTotal": "85",
         "terrenoEdificado": "85",
         "cantDormitorios": "2",
         "cantBanos": "1",
         "cantCochera": "1",
         "barrio": "20 DE JUNIO",
         "ciudad": "CORDOBA",
         "coordX": -31.4090106,
         "coordY": -64.2622432,
         "activo": false,
         "URL": "https://www.zonaprop.com.ar/propiedades/venta-duplex-2-dorm-cochera-patio-20-de-junio-50823412.html"
},{
         "id": "50824457",
         "tipoPropiedad": "CASA",
         "precioUSD": 170000,
         "fechaUltimaActualizacion": "11-12-2022",
         "vendedor": "INMOBILIARIA",
         "terrenoTotal": "180",
         "terrenoEdificado": "175",
         "cantDormitorios": "3",
         "cantBanos": "3",
         "cantCochera": "2",
         "barrio": "GREENVILLE II",
         "ciudad": "CORDOBA",
         "coordX": -31.4842449,
         "coordY": -64.1689224,
         "activo": false,
         "URL": "https://www.zonaprop.com.ar/propiedades/venta-duplex-greenville-2-50824457.html"
},{
         "id": "50825142",
         "tipoPropiedad": "DEPARTAMENTO",
         "precioUSD": 155000,
         "fechaUltimaActualizacion": "07-12-2022",
         "vendedor": "INMOBILIARIA",
         "terrenoTotal": "122",
         "terrenoEdificado": "71",
         "cantDormitorios": "2",
         "cantBanos": "2",
         "cantCochera": -1,
         "barrio": "GENERAL PAZ",
         "ciudad": "CORDOBA",
         "coordX": -31.4160802,
         "coordY": -64.1678777,
         "activo": false,
         "URL": "https://www.zonaprop.com.ar/propiedades/escritura-inmediata-balcones-9-depto-2d-2b-en-g-paz-50825142.html"
},{
         "id": "50825579",
         "tipoPropiedad": "TERRENOS",
         "precioUSD": 6000,
         "fechaUltimaActualizacion": "07-12-2022",
         "vendedor": "INMOBILIARIA",
         "terrenoTotal": "1000",
         "terrenoEdificado": -1,
         "cantDormitorios": -1,
         "cantBanos": -1,
         "cantCochera": -1,
         "barrio": "VENTA 3 LOTES TANTI 1000 M2",
         "ciudad": "TANTI",
         "coordX": -31.36422318303,
         "coordY": -64.603761434555,
         "activo": false,
         "URL": "https://www.zonaprop.com.ar/propiedades/venta-3-lotes-tanti-1000-m-sup2-50825579.html"
},{
         "id": "50891947",
         "tipoPropiedad": "TERRENOS",
         "precioUSD": 17000,
         "fechaUltimaActualizacion": "23-12-2022",
         "vendedor": "INMOBILIARIA",
         "terrenoTotal": "600",
         "terrenoEdificado": -1,
         "cantDormitorios": -1,
         "cantBanos": -1,
         "cantCochera": -1,
         "barrio": "VENTA TERRENO 600 M2 CABALANGO ESCRITURA",
         "ciudad": "CABALANGO",
         "coordX": -31.388190131936,
         "coordY": -64.556849598885,
         "activo": false,
         "URL": "https://www.zonaprop.com.ar/propiedades/venta-terreno-600-m-sup2--cabalango-escritura-50891947.html"
}]