[{
         "id": "42436552",
         "tipoPropiedad": "CASA",
         "precioUSD": 220000,
         "fechaUltimaActualizacion": "01-08-2022",
         "vendedor": "PARTICULAR",
         "terrenoTotal": "1687",
         "terrenoEdificado": "265",
         "cantDormitorios": "3",
         "cantBanos": "2",
         "cantCochera": "1",
         "barrio": "EL TALAR",
         "ciudad": "MENDIOLAZA",
         "coordX": -31.2561908,
         "coordY": -64.2755057,
         "activo": false,
         "URL": "https://www.zonaprop.com.ar/propiedades/venta-mendiolaza-talar-casa-3-dorm.-apta-credito-42436552.html"
},{
         "id": "42445221",
         "tipoPropiedad": "CASA",
         "precioUSD": 210000,
         "fechaUltimaActualizacion": "01-08-2022",
         "vendedor": "INMOBILIARIA",
         "terrenoTotal": -1,
         "terrenoEdificado": -1,
         "cantDormitorios": "3",
         "cantBanos": "3",
         "cantCochera": -1,
         "barrio": "INMEJORABLE CONSTRUCCION CON TRES DORMIT",
         "ciudad": "CORDOBA",
         "coordX": -31.443164,
         "coordY": -64.1986697,
         "activo": false,
         "URL": "https://www.zonaprop.com.ar/propiedades/inmejorable-construccion-con-tres-dormit-42445221.html"
},{
         "id": "42450699",
         "tipoPropiedad": "CASA",
         "precioUSD": 110000,
         "fechaUltimaActualizacion": "01-08-2022",
         "vendedor": "INMOBILIARIA",
         "terrenoTotal": "760",
         "terrenoEdificado": "142",
         "cantDormitorios": "3",
         "cantBanos": "2",
         "cantCochera": -1,
         "barrio": "ARGUELLO",
         "ciudad": "CORDOBA",
         "coordX": -31.3356513,
         "coordY": -64.2703538,
         "activo": false,
         "URL": "https://www.zonaprop.com.ar/propiedades/arguello-montufar-y-coronado-7400-venta-casa-3-42450699.html"
},{
         "id": "42471706",
         "tipoPropiedad": "TERRENOS",
         "precioUSD": 35000,
         "fechaUltimaActualizacion": "01-08-2022",
         "vendedor": "INMOBILIARIA",
         "terrenoTotal": "1506",
         "terrenoEdificado": "1",
         "cantDormitorios": -1,
         "cantBanos": -1,
         "cantCochera": -1,
         "barrio": "LA CUMBRE - TERRENO EN ZONA RESIDENCIAL PROXIMA A CRUZ CHICA",
         "ciudad": "LA CUMBRE",
         "coordX": -30.976974,
         "coordY": -64.4831481,
         "activo": false,
         "URL": "https://www.zonaprop.com.ar/propiedades/la-cumbre-terreno-en-zona-residencial-proxima-a-cruz-42471706.html"
},{
         "id": "42480219",
         "tipoPropiedad": "CASA",
         "precioUSD": 180000,
         "fechaUltimaActualizacion": "01-08-2022",
         "vendedor": "INMOBILIARIA",
         "terrenoTotal": "1200",
         "terrenoEdificado": "200",
         "cantDormitorios": "4",
         "cantBanos": "2",
         "cantCochera": -1,
         "barrio": "LA CUMBRE - CRUZ GRANDE",
         "ciudad": "LA CUMBRE",
         "coordX": -30.982372,
         "coordY": -64.4970309,
         "activo": false,
         "URL": "https://www.zonaprop.com.ar/propiedades/la-cumbre-cruz-grande-42480219.html"
},{
         "id": "42495906",
         "tipoPropiedad": "TERRENOS",
         "precioUSD": 450000,
         "fechaUltimaActualizacion": "01-08-2022",
         "vendedor": "INMOBILIARIA",
         "terrenoTotal": "2540",
         "terrenoEdificado": -1,
         "cantDormitorios": -1,
         "cantBanos": -1,
         "cantCochera": -1,
         "barrio": "VILLA CORNU (DONATO ALVAREZ 9000) - VENTA 4 TERRENOS 644 M2",
         "ciudad": "CORDOBA",
         "coordX": -31.32026419999999,
         "coordY": -64.271598,
         "activo": false,
         "URL": "https://www.zonaprop.com.ar/propiedades/villa-cornu-donato-alvarez-9000-venta-4-terrenos-42495906.html"
},{
         "id": "42507022",
         "tipoPropiedad": "CASA",
         "precioUSD": 368000,
         "fechaUltimaActualizacion": "01-08-2022",
         "vendedor": "INMOBILIARIA",
         "terrenoTotal": "675",
         "terrenoEdificado": "275",
         "cantDormitorios": "4",
         "cantBanos": "2",
         "cantCochera": "2",
         "barrio": "CERRO DE LAS ROSAS",
         "ciudad": "CORDOBA",
         "coordX": -31.3751564,
         "coordY": -64.23316956,
         "activo": false,
         "URL": "https://www.zonaprop.com.ar/propiedades/cerro-sobre-malbran-impecable-con-pileta!-42507022.html"
},{
         "id": "42519833",
         "tipoPropiedad": "TERRENOS",
         "precioUSD": 45000,
         "fechaUltimaActualizacion": "01-08-2022",
         "vendedor": "INMOBILIARIA",
         "terrenoTotal": "35000",
         "terrenoEdificado": -1,
         "cantDormitorios": -1,
         "cantBanos": -1,
         "cantCochera": -1,
         "barrio": "EXCELENTE TERRENO EN CORDOBA EXCLUSIVO PARA HOTELERIA!",
         "ciudad": "LAS HIGUERAS",
         "coordX": -31.01377106,
         "coordY": -65.10219574,
         "activo": false,
         "URL": "https://www.zonaprop.com.ar/propiedades/excelente-terreno-en-cordoba-exclusivo-para-hoteleria!-42519833.html"
},{
         "id": "42564910",
         "tipoPropiedad": "CASA",
         "precioUSD": 180000,
         "fechaUltimaActualizacion": "01-08-2022",
         "vendedor": "INMOBILIARIA",
         "terrenoTotal": "541",
         "terrenoEdificado": "240",
         "cantDormitorios": "3",
         "cantBanos": "3",
         "cantCochera": -1,
         "barrio": "PARQUE CAPITAL 3 DORM",
         "ciudad": "CORDOBA",
         "coordX": -31.4312945,
         "coordY": -64.2173351999999,
         "activo": false,
         "URL": "https://www.zonaprop.com.ar/propiedades/parque-capital-3-dorm-42564910.html"
},{
         "id": "42568425",
         "tipoPropiedad": "DEPARTAMENTO",
         "precioUSD": 45000,
         "fechaUltimaActualizacion": "01-08-2022",
         "vendedor": "INMOBILIARIA",
         "terrenoTotal": "50",
         "terrenoEdificado": "45",
         "cantDormitorios": "1",
         "cantBanos": "1",
         "cantCochera": -1,
         "barrio": "ALBERDI",
         "ciudad": "CORDOBA",
         "coordX": -31.40910119999999,
         "coordY": -64.194403,
         "activo": false,
         "URL": "https://www.zonaprop.com.ar/propiedades/alberdi-sta-rosa-800-1-dor-con-amplia-terraza-42568425.html"
},{
         "id": "42586832",
         "tipoPropiedad": "TERRENOS",
         "precioUSD": 80000,
         "fechaUltimaActualizacion": "01-08-2022",
         "vendedor": "INMOBILIARIA",
         "terrenoTotal": "827",
         "terrenoEdificado": -1,
         "cantDormitorios": -1,
         "cantBanos": -1,
         "cantCochera": -1,
         "barrio": "C. PAZ HERMOSO Y EXCLUSIVO LOTE EN VILLA DEL LAGO",
         "ciudad": "VILLA CARLOS PAZ",
         "coordX": -31.397212475747125,
         "coordY": -64.49688799947512,
         "activo": false,
         "URL": "https://www.zonaprop.com.ar/propiedades/c.-paz-hermoso-y-exclusivo-lote-en-villa-del-lago-42586832.html"
},{
         "id": "42586854",
         "tipoPropiedad": "CASA",
         "precioUSD": 1050000,
         "fechaUltimaActualizacion": "01-08-2022",
         "vendedor": "INMOBILIARIA",
         "terrenoTotal": "8000",
         "terrenoEdificado": "880",
         "cantDormitorios": -1,
         "cantBanos": -1,
         "cantCochera": "9",
         "barrio": "CARLOS PAZ VENDO COMPLEJO DE CABANAS",
         "ciudad": "VILLA CARLOS PAZ",
         "coordX": -31.3925049,
         "coordY": -64.51287100000002,
         "activo": false,
         "URL": "https://www.zonaprop.com.ar/propiedades/carlos-paz-vendo-complejo-de-cabanas-42586854.html"
},{
         "id": "42586862",
         "tipoPropiedad": "TERRENOS",
         "precioUSD": 70000,
         "fechaUltimaActualizacion": "01-08-2022",
         "vendedor": "INMOBILIARIA",
         "terrenoTotal": "1291",
         "terrenoEdificado": -1,
         "cantDormitorios": -1,
         "cantBanos": -1,
         "cantCochera": -1,
         "barrio": "V. C. PAZ URGENTE OPORTUNIDAD LOTE EN VILLA DEL LAGO",
         "ciudad": "VILLA CARLOS PAZ",
         "coordX": -31.3932577,
         "coordY": -64.50145320000001,
         "activo": false,
         "URL": "https://www.zonaprop.com.ar/propiedades/v.-c.-paz-urgente-oportunidad-lote-en-villa-del-lago-42586862.html"
},{
         "id": "42611934",
         "tipoPropiedad": "CASA",
         "precioUSD": 160000,
         "fechaUltimaActualizacion": "01-08-2022",
         "vendedor": "INMOBILIARIA",
         "terrenoTotal": "2500",
         "terrenoEdificado": "190",
         "cantDormitorios": "4",
         "cantBanos": "3",
         "cantCochera": -1,
         "barrio": "YACANTO",
         "ciudad": "SAN JAVIER",
         "coordX": -32.0499992,
         "coordY": -65.0500107,
         "activo": false,
         "URL": "https://www.zonaprop.com.ar/propiedades/-el-rancho-magnifica-casa-a-la-venta-en-yacanto-42611934.html"
},{
         "id": "42641619",
         "tipoPropiedad": "CASA",
         "precioUSD": 140000,
         "fechaUltimaActualizacion": "01-08-2022",
         "vendedor": "INMOBILIARIA",
         "terrenoTotal": "150",
         "terrenoEdificado": "150",
         "cantDormitorios": "3",
         "cantBanos": "2",
         "cantCochera": -1,
         "barrio": "QUEBRADA DE LAS ROSAS",
         "ciudad": "CORDOBA",
         "coordX": -31.399076,
         "coordY": -64.2507267,
         "activo": false,
         "URL": "https://www.zonaprop.com.ar/propiedades/barrio-quebrada-las-rosas-3-dor-coch-pat-impecable-42641619.html"
},{
         "id": "42657043",
         "tipoPropiedad": "CASA",
         "precioUSD": 220000,
         "fechaUltimaActualizacion": "01-08-2022",
         "vendedor": "INMOBILIARIA",
         "terrenoTotal": "759",
         "terrenoEdificado": "273",
         "cantDormitorios": "4",
         "cantBanos": "3",
         "cantCochera": -1,
         "barrio": "CERRO DE LAS ROSAS",
         "ciudad": "CORDOBA",
         "coordX": -31.3717317,
         "coordY": -64.2354692,
         "activo": false,
         "URL": "https://www.zonaprop.com.ar/propiedades/ideal-inversor-empresa-comercio.-42657043.html"
},{
         "id": "41132067",
         "tipoPropiedad": "CASA",
         "precioUSD": 310000,
         "fechaUltimaActualizacion": "01-08-2022",
         "vendedor": "INMOBILIARIA",
         "terrenoTotal": "2379",
         "terrenoEdificado": "330",
         "cantDormitorios": "4",
         "cantBanos": "3",
         "cantCochera": "3",
         "barrio": "LA CUMBRE - CRUZ CHICA - CHALET HARMONIA",
         "ciudad": "LA CUMBRE",
         "coordX": -30.9706449,
         "coordY": -64.48643329999999,
         "activo": false,
         "URL": "https://www.zonaprop.com.ar/propiedades/la-cumbre-cruz-chica-chalet-harmonia-41132067.html"
},{
         "id": "41284181",
         "tipoPropiedad": "TERRENOS",
         "precioUSD": 35000,
         "fechaUltimaActualizacion": "01-08-2022",
         "vendedor": "INMOBILIARIA",
         "terrenoTotal": "1506",
         "terrenoEdificado": -1,
         "cantDormitorios": -1,
         "cantBanos": -1,
         "cantCochera": -1,
         "barrio": "LA CUMBRE - TERRENO 1500 M ANTIGUO CAMINO A CRUZ CHICA",
         "ciudad": "LA CUMBRE",
         "coordX": -30.9879066,
         "coordY": -64.4810453,
         "activo": false,
         "URL": "https://www.zonaprop.com.ar/propiedades/la-cumbre-terreno-1500-m-antiguo-camino-a-cruz-chica-41284181.html"
},{
         "id": "41284287",
         "tipoPropiedad": "CASA",
         "precioUSD": 190000,
         "fechaUltimaActualizacion": "01-08-2022",
         "vendedor": "PARTICULAR",
         "terrenoTotal": "1510",
         "terrenoEdificado": "178",
         "cantDormitorios": "3",
         "cantBanos": "2",
         "cantCochera": "1",
         "barrio": "LA CUMBRE - CASA DE CATEGORIA ZONA CRUZ CHICA",
         "ciudad": "LA CUMBRE",
         "coordX": -30.9706449,
         "coordY": -64.48643329999999,
         "activo": false,
         "URL": "https://www.zonaprop.com.ar/propiedades/la-cumbre-casa-de-categoria-zona-cruz-chica-41284287.html"
},{
         "id": "41456056",
         "tipoPropiedad": "CASA",
         "precioUSD": 136000,
         "fechaUltimaActualizacion": "01-08-2022",
         "vendedor": "INMOBILIARIA",
         "terrenoTotal": "2500",
         "terrenoEdificado": "70",
         "cantDormitorios": "2",
         "cantBanos": "1",
         "cantCochera": -1,
         "barrio": "LA CUMBRE - CAMINO AL DIQUE SAN GERONIMO",
         "ciudad": "LA CUMBRE",
         "coordX": -30.982372,
         "coordY": -64.4970309,
         "activo": false,
         "URL": "https://www.zonaprop.com.ar/propiedades/la-cumbre-camino-al-dique-san-geronimo-41456056.html"
}]