[{
         "id": "1440902580",
         "tipoPropiedad": "CASA",
         "precioUSD": 2200000,
         "fechaUltimaActualizacion": "30-06-2023",
         "vendedor": "INMOBILIARIA",
         "terrenoTotal": 600,
         "terrenoEdificado": 500,
         "cantDormitorios": 18,
         "cantBanos": 5,
         "cantCochera": 2,
         "barrio": "PARQUE SARMIENTO",
         "ciudad": "CORDOBA",
         "coordX": -31.4296254,
         "coordY": -64.1848181,
         "activo": true,
         "URL": "https://casa.mercadolibre.com.ar/MLA-1440902580-importante-casona-en-venta-sobre-hipolito-yrigoyen-_JM"
},{
         "id": "1276577084",
         "tipoPropiedad": "CASA",
         "precioUSD": 215000,
         "fechaUltimaActualizacion": "03-01-2023",
         "vendedor": "INMOBILIARIA",
         "terrenoTotal": 350,
         "terrenoEdificado": 272,
         "cantDormitorios": 3,
         "cantBanos": 3,
         "cantCochera": 2,
         "barrio": "PARQUE SARMIENTO",
         "ciudad": "CORDOBA",
         "coordX": -31.4316505,
         "coordY": -64.1842231,
         "activo": false,
         "URL": "https://casa.mercadolibre.com.ar/MLA-1276577084-moderna-casa-en-venta-_JM"
}]